{"n0": {"n1": [[["n0", "n1"], 97], [["n0", "n5", "n1"], 183.43], [["n0", "n3", "n5", "n1"], 254.43]], "n2": [[["n0", "n1", "n2"], 240.78], [["n0", "n1", "n4", "n2"], 285.02], [["n0", "n5", "n1", "n2"], 327.21000000000004]], "n3": [[["n0", "n3"], 69.0], [["n0", "n5", "n3"], 184.0], [["n0", "n1", "n5", "n3"], 282.43]], "n4": [[["n0", "n1", "n4"], 177.57999999999998], [["n0", "n5", "n4"], 225.0], [["n0", "n5", "n1", "n4"], 264.01]], "n5": [[["n0", "n5"], 91.0], [["n0", "n3", "n5"], 162.0], [["n0", "n1", "n5"], 189.43]], "n6": [[["n0", "n5", "n6"], 184.0], [["n0", "n3", "n6"], 190.0], [["n0", "n3", "n5", "n6"], 255.0]], "n7": [[["n0", "n1", "n4", "n7"], 282.58], [["n0", "n5", "n6", "n7"], 314.0], [["n0", "n3", "n6", "n7"], 320.0]]}, "n1": {"n0": [[["n1", "n0"], 97], [["n1", "n5", "n0"], 183.43], [["n1", "n5", "n3", "n0"], 254.43]], "n2": [[["n1", "n2"], 143.78], [["n1", "n4", "n2"], 188.01999999999998], [["n1", "n4", "n7", "n2"], 272.48]], "n3": [[["n1", "n0", "n3"], 166.0], [["n1", "n5", "n3"], 185.43], [["n1", "n5", "n0", "n3"], 252.43]], "n4": [[["n1", "n4"], 80.58], [["n1", "n5", "n4"], 226.43], [["n1", "n2", "n4"], 251.22]], "n5": [[["n1", "n5"], 92.43], [["n1", "n0", "n5"], 188.0], [["n1", "n4", "n5"], 214.57999999999998]], "n6": [[["n1", "n5", "n6"], 185.43], [["n1", "n0", "n5", "n6"], 281.0], [["n1", "n0", "n3", "n6"], 287.0]], "n7": [[["n1", "n4", "n7"], 185.57999999999998], [["n1", "n2", "n7"], 230.68], [["n1", "n4", "n2", "n7"], 274.91999999999996]]}, "n2": {"n0": [[["n2", "n1", "n0"], 240.78], [["n2", "n4", "n1", "n0"], 285.02], [["n2", "n1", "n5", "n0"], 327.21000000000004]], "n1": [[["n2", "n1"], 143.78], [["n2", "n4", "n1"], 188.01999999999998], [["n2", "n7", "n4", "n1"], 272.48]], "n3": [[["n2", "n1", "n0", "n3"], 309.78], [["n2", "n1", "n5", "n3"], 329.21000000000004], [["n2", "n4", "n5", "n3"], 334.44]], "n4": [[["n2", "n4"], 107.44], [["n2", "n7", "n4"], 191.9], [["n2", "n1", "n4"], 224.36]], "n5": [[["n2", "n1", "n5"], 236.21], [["n2", "n4", "n5"], 241.44], [["n2", "n4", "n1", "n5"], 280.45]], "n6": [[["n2", "n7", "n6"], 216.9], [["n2", "n1", "n5", "n6"], 329.21000000000004], [["n2", "n4", "n5", "n6"], 334.44]], "n7": [[["n2", "n7"], 86.9], [["n2", "n4", "n7"], 212.44], [["n2", "n1", "n4", "n7"], 329.36]]}, "n3": {"n0": [[["n3", "n0"], 69.0], [["n3", "n5", "n0"], 184.0], [["n3", "n5", "n1", "n0"], 282.43]], "n1": [[["n3", "n0", "n1"], 166.0], [["n3", "n5", "n1"], 185.43], [["n3", "n0", "n5", "n1"], 252.43]], "n2": [[["n3", "n0", "n1", "n2"], 309.78], [["n3", "n5", "n1", "n2"], 329.21000000000004], [["n3", "n5", "n4", "n2"], 334.44]], "n4": [[["n3", "n5", "n4"], 227.0], [["n3", "n0", "n1", "n4"], 246.57999999999998], [["n3", "n5", "n1", "n4"], 266.01]], "n5": [[["n3", "n5"], 93.0], [["n3", "n0", "n5"], 160.0], [["n3", "n6", "n5"], 214.0]], "n6": [[["n3", "n6"], 121.0], [["n3", "n5", "n6"], 186.0], [["n3", "n0", "n5", "n6"], 253.0]], "n7": [[["n3", "n6", "n7"], 251.0], [["n3", "n5", "n6", "n7"], 316.0], [["n3", "n5", "n4", "n7"], 332.0]]}, "n4": {"n0": [[["n4", "n1", "n0"], 177.57999999999998], [["n4", "n5", "n0"], 225.0], [["n4", "n1", "n5", "n0"], 264.01]], "n1": [[["n4", "n1"], 80.58], [["n4", "n5", "n1"], 226.43], [["n4", "n2", "n1"], 251.22]], "n2": [[["n4", "n2"], 107.44], [["n4", "n7", "n2"], 191.9], [["n4", "n1", "n2"], 224.36]], "n3": [[["n4", "n5", "n3"], 227.0], [["n4", "n1", "n0", "n3"], 246.57999999999998], [["n4", "n1", "n5", "n3"], 266.01]], "n5": [[["n4", "n5"], 134.0], [["n4", "n1", "n5"], 173.01], [["n4", "n1", "n0", "n5"], 268.58]], "n6": [[["n4", "n5", "n6"], 227.0], [["n4", "n7", "n6"], 235.0], [["n4", "n1", "n5", "n6"], 266.01]], "n7": [[["n4", "n7"], 105.0], [["n4", "n2", "n7"], 194.34], [["n4", "n1", "n2", "n7"], 311.26]]}, "n5": {"n0": [[["n5", "n0"], 91.0], [["n5", "n3", "n0"], 162.0], [["n5", "n1", "n0"], 189.43]], "n1": [[["n5", "n1"], 92.43], [["n5", "n0", "n1"], 188.0], [["n5", "n4", "n1"], 214.57999999999998]], "n2": [[["n5", "n1", "n2"], 236.21], [["n5", "n4", "n2"], 241.44], [["n5", "n1", "n4", "n2"], 280.45]], "n3": [[["n5", "n3"], 93.0], [["n5", "n0", "n3"], 160.0], [["n5", "n6", "n3"], 214.0]], "n4": [[["n5", "n4"], 134.0], [["n5", "n1", "n4"], 173.01], [["n5", "n0", "n1", "n4"], 268.58]], "n6": [[["n5", "n6"], 93.0], [["n5", "n3", "n6"], 214.0], [["n5", "n0", "n3", "n6"], 281.0]], "n7": [[["n5", "n6", "n7"], 223.0], [["n5", "n4", "n7"], 239.0], [["n5", "n1", "n4", "n7"], 278.01]]}, "n6": {"n0": [[["n6", "n5", "n0"], 184.0], [["n6", "n3", "n0"], 190.0], [["n6", "n5", "n3", "n0"], 255.0]], "n1": [[["n6", "n5", "n1"], 185.43], [["n6", "n5", "n0", "n1"], 281.0], [["n6", "n3", "n0", "n1"], 287.0]], "n2": [[["n6", "n7", "n2"], 216.9], [["n6", "n5", "n1", "n2"], 329.21000000000004], [["n6", "n5", "n4", "n2"], 334.44]], "n3": [[["n6", "n3"], 121.0], [["n6", "n5", "n3"], 186.0], [["n6", "n5", "n0", "n3"], 253.0]], "n4": [[["n6", "n5", "n4"], 227.0], [["n6", "n7", "n4"], 235.0], [["n6", "n5", "n1", "n4"], 266.01]], "n5": [[["n6", "n5"], 93.0], [["n6", "n3", "n5"], 214.0], [["n6", "n3", "n0", "n5"], 281.0]], "n7": [[["n6", "n7"], 130.0], [["n6", "n5", "n4", "n7"], 332.0], [["n6", "n5", "n1", "n4", "n7"], 371.01]]}, "n7": {"n0": [[["n7", "n4", "n1", "n0"], 282.58], [["n7", "n6", "n5", "n0"], 314.0], [["n7", "n6", "n3", "n0"], 320.0]], "n1": [[["n7", "n4", "n1"], 185.57999999999998], [["n7", "n2", "n1"], 230.68], [["n7", "n2", "n4", "n1"], 274.92]], "n2": [[["n7", "n2"], 86.9], [["n7", "n4", "n2"], 212.44], [["n7", "n4", "n1", "n2"], 329.36]], "n3": [[["n7", "n6", "n3"], 251.0], [["n7", "n6", "n5", "n3"], 316.0], [["n7", "n4", "n5", "n3"], 332.0]], "n4": [[["n7", "n4"], 105.0], [["n7", "n2", "n4"], 194.34], [["n7", "n2", "n1", "n4"], 311.26]], "n5": [[["n7", "n6", "n5"], 223.0], [["n7", "n4", "n5"], 239.0], [["n7", "n4", "n1", "n5"], 278.01]], "n6": [[["n7", "n6"], 130.0], [["n7", "n4", "n5", "n6"], 332.0], [["n7", "n4", "n1", "n5", "n6"], 371.01]]}}